{
  "took": 768,
  "timed_out": false,
  "_shards": {
    "total": 292,
    "successful": 292,
    "skipped": 290,
    "failed": 0
  },
  "hits": {
    "total": 4576175,
    "max_score": null,
    "hits": []
  },
  "aggregations": {
    "terms": {
      "doc_count_error_upper_bound": 0,
      "sum_other_doc_count": 0,
      "buckets": [
        {
          "key": "Cable",
          "doc_count": 1997745,
          "cdf": {
            "values": [
              {
                "key": 0,
                "value": 2131
              },
              {
                "key": 5,
                "value": 13026.840330447822
              },
              {
                "key": 10,
                "value": 15886.386751364726
              },
              {
                "key": 15,
                "value": 17294.588142493292
              },
              {
                "key": 20,
                "value": 18486.74323935052
              },
              {
                "key": 25,
                "value": 19548.635676847578
              },
              {
                "key": 30,
                "value": 20633.54541822979
              },
              {
                "key": 35,
                "value": 21769.931164741356
              },
              {
                "key": 40,
                "value": 22926.7539359806
              },
              {
                "key": 45,
                "value": 24178.472914030568
              },
              {
                "key": 50,
                "value": 25430.191892080533
              },
              {
                "key": 55,
                "value": 26898.323950249618
              },
              {
                "key": 60,
                "value": 28465.088161496707
              },
              {
                "key": 65,
                "value": 30124.66854814098
              },
              {
                "key": 70,
                "value": 32152.403188650947
              },
              {
                "key": 75,
                "value": 34328.2929347421
              },
              {
                "key": 80,
                "value": 37607.85628673431
              },
              {
                "key": 85,
                "value": 41942.90673138432
              },
              {
                "key": 90,
                "value": 49423.91440824971
              },
              {
                "key": 95,
                "value": 70718.29353068242
              },
              {
                "key": 96,
                "value": 81141.82269698547
              },
              {
                "key": 97,
                "value": 98453.1078196942
              },
              {
                "key": 98,
                "value": 134787.06574042517
              },
              {
                "key": 98.5,
                "value": 161260.88676053577
              },
              {
                "key": 99,
                "value": 184339.38881679566
              },
              {
                "key": 99.5,
                "value": 215730.43722482517
              },
              {
                "key": 99.9,
                "value": 278244.8593594422
              },
              {
                "key": 100,
                "value": 479032
              }
            ]
          }
        },
        {
          "key": "DSL",
          "doc_count": 1400645,
          "cdf": {
            "values": [
              {
                "key": 0,
                "value": 1573
              },
              {
                "key": 5,
                "value": 11466.730915555954
              },
              {
                "key": 10,
                "value": 15157.390112675508
              },
              {
                "key": 15,
                "value": 17612.932617613074
              },
              {
                "key": 20,
                "value": 19786.242674798144
              },
              {
                "key": 25,
                "value": 22102.041883889764
              },
              {
                "key": 30,
                "value": 24411.02122696264
              },
              {
                "key": 35,
                "value": 26672.45579500559
              },
              {
                "key": 40,
                "value": 29092.094228655827
              },
              {
                "key": 45,
                "value": 31622.152209650063
              },
              {
                "key": 50,
                "value": 34387.22094013794
              },
              {
                "key": 55,
                "value": 37637.760964655536
              },
              {
                "key": 60,
                "value": 40888.30098917313
              },
              {
                "key": 65,
                "value": 45537.34650980827
              },
              {
                "key": 70,
                "value": 50283.95485347959
              },
              {
                "key": 75,
                "value": 57671.26164946855
              },
              {
                "key": 80,
                "value": 66139.1774882493
              },
              {
                "key": 85,
                "value": 79722.82536395015
              },
              {
                "key": 90,
                "value": 101555.849554539
              },
              {
                "key": 95,
                "value": 151030.42672708805
              },
              {
                "key": 96,
                "value": 170663.58163333073
              },
              {
                "key": 97,
                "value": 194878.12894214425
              },
              {
                "key": 98,
                "value": 227638.8160063384
              },
              {
                "key": 98.5,
                "value": 249437.7332895205
              },
              {
                "key": 99,
                "value": 278926.3404640863
              },
              {
                "key": 99.5,
                "value": 312594.95157477603
              },
              {
                "key": 99.9,
                "value": 659452.8668390594
              },
              {
                "key": 100,
                "value": 957404
              }
            ]
          }
        },
        {
          "key": "Fiber",
          "doc_count": 1177785,
          "cdf": {
            "values": [
              {
                "key": 0,
                "value": 1365
              },
              {
                "key": 5,
                "value": 4460.730383073828
              },
              {
                "key": 10,
                "value": 5443.193719818112
              },
              {
                "key": 15,
                "value": 6235.687722211203
              },
              {
                "key": 20,
                "value": 6999.803756794413
              },
              {
                "key": 25,
                "value": 7870.805217760649
              },
              {
                "key": 30,
                "value": 8805.736469241252
              },
              {
                "key": 35,
                "value": 9794.54867934631
              },
              {
                "key": 40,
                "value": 10787.875372020833
              },
              {
                "key": 45,
                "value": 11788.262073512282
              },
              {
                "key": 50,
                "value": 12788.64877500373
              },
              {
                "key": 55,
                "value": 13752.97871926147
              },
              {
                "key": 60,
                "value": 14715.200801307583
              },
              {
                "key": 65,
                "value": 15708.356762043926
              },
              {
                "key": 70,
                "value": 16715.669478817756
              },
              {
                "key": 75,
                "value": 17930.061618197706
              },
              {
                "key": 80,
                "value": 19519.707455798456
              },
              {
                "key": 85,
                "value": 22117.637035108783
              },
              {
                "key": 90,
                "value": 27887.577587157197
              },
              {
                "key": 95,
                "value": 46116.37209602483
              },
              {
                "key": 96,
                "value": 52748.30867740833
              },
              {
                "key": 97,
                "value": 65512.561331153345
              },
              {
                "key": 98,
                "value": 85171.90315062508
              },
              {
                "key": 98.5,
                "value": 101475.00851421308
              },
              {
                "key": 99,
                "value": 119446.63035866743
              },
              {
                "key": 99.5,
                "value": 155531.38369949113
              },
              {
                "key": 99.9,
                "value": 270107.8320260489
              },
              {
                "key": 100,
                "value": 626058
              }
            ]
          }
        }
      ]
    }
  }
}